catacomb/__init__.py
catacomb/entry_points.py
catacomb/settings.py
catacomb/commands/__init__.py
catacomb/commands/catacomb/__init__.py
catacomb/commands/catacomb/bury.py
catacomb/commands/catacomb/create.py
catacomb/commands/catacomb/list.py
catacomb/commands/catacomb/open.py
catacomb/commands/tomb/__init__.py
catacomb/commands/tomb/add.py
catacomb/commands/tomb/clean.py
catacomb/commands/tomb/edit.py
catacomb/commands/tomb/list.py
catacomb/commands/tomb/rm.py
catacomb/commands/tomb/status.py
catacomb/commands/tomb/use.py
catacomb/common/__init__.py
catacomb/common/about.py
catacomb/common/constants.py
catacomb/common/errors.py
catacomb/decorators/__init__.py
catacomb/decorators/context.py
catacomb/utils/__init__.py
catacomb/utils/catacomb_handler.py
catacomb/utils/file_handler.py
catacomb/utils/formatter.py
catacomb/utils/helpers.py
catacomb/utils/plugin_loader.py
catacomb/utils/tomb_handler.py
catacomb-0.5.1.dist-info/DESCRIPTION.rst
catacomb-0.5.1.dist-info/METADATA
catacomb-0.5.1.dist-info/RECORD
catacomb-0.5.1.dist-info/WHEEL
catacomb-0.5.1.dist-info/entry_points.txt
catacomb-0.5.1.dist-info/metadata.json
catacomb-0.5.1.dist-info/top_level.txt
