Metadata-Version: 2.0
Name: catacomb
Version: 0.5.1
Summary: A minimalistic CLI tool for storing shell commands.
Home-page: https://github.com/mitchjeitani/catacomb
Author: Mitchell Jeitani
Author-email: mitchelljeitani@gmail.com
License: MIT
Keywords: command-line shell productivity storage
Platform: UNKNOWN
Requires-Dist: click
Requires-Dist: terminaltables
